{
  "ComponentIndexes": {
    "_headder": 2,
    "_menu": 4,
    "_sidebar": 3,
    "sidebar_e": 4
  },
  "ControlUniqueGuids": {},
  "ControlUniqueIds": {
    "_broj": 12,
    "_Broj_1": 19,
    "_color": 11,
    "_evidencija": 24,
    "_footer": 22,
    "_galEvidencija": 26,
    "_galNaslov": 29,
    "_galPodnaslov": 31,
    "_galPodnaslov_1": 32,
    "_galSjena": 30,
    "_galSlika": 28,
    "_gumb": 14,
    "_headder": 4,
    "_logo": 7,
    "_menu": 6,
    "_naslov": 8,
    "_Natpis_1": 20,
    "_nav": 9,
    "_nav_lower": 15,
    "_pacjent:_datum_rodenja_DataCard1": 61,
    "_pacjent:_ime_DataCard1": 51,
    "_pacjent:_prezime_DataCard1": 56,
    "_pacjent_DataCard1": 46,
    "_sidebar": 3,
    "_sjena_1": 17,
    "_text": 13,
    "App": 1,
    "block_1": 18,
    "Button3": 21,
    "DataCardKey2": 42,
    "DataCardKey3": 47,
    "DataCardKey4": 52,
    "DataCardKey5": 57,
    "DataCardKey6": 62,
    "DataCardKey7": 67,
    "DataCardKey8": 72,
    "DataCardKey9": 77,
    "DataCardValue2": 43,
    "DataCardValue3": 48,
    "DataCardValue4": 53,
    "DataCardValue5": 58,
    "DataCardValue6": 63,
    "DataCardValue7": 68,
    "DataCardValue8": 73,
    "DataCardValue9": 78,
    "ErrorMessage2": 44,
    "ErrorMessage3": 49,
    "ErrorMessage4": 54,
    "ErrorMessage5": 59,
    "ErrorMessage6": 64,
    "ErrorMessage7": 69,
    "ErrorMessage8": 74,
    "ErrorMessage9": 79,
    "Form2": 40,
    "galleryTemplate1": 10,
    "galleryTemplate1_1": 16,
    "galleryTemplate2": 27,
    "Home": 23,
    "link_zahvat_DataCard1": 76,
    "oper:Title_DataCard1": 71,
    "oper_DataCard1": 66,
    "Separator1": 33,
    "sidebar_e": 25,
    "sjena": 5,
    "StarVisible2": 45,
    "StarVisible3": 50,
    "StarVisible4": 55,
    "StarVisible5": 60,
    "StarVisible6": 65,
    "StarVisible7": 70,
    "StarVisible8": 75,
    "StarVisible9": 80,
    "Title_DataCard1": 41
  },
  "FunctionParamsInvariantScripts": {},
  "FunctionParamsInvariantScriptsOnInstances": {},
  "HeaderLastSavedDateTimeUTC": "02/27/2023 12:43:23",
  "IsLegacyComponentAllowGlobalScopeCase": false,
  "LocalConnectionIDReferences": {
    "0175a8bd-2c5d-4709-ba25-8883d71e2e1d": "\"/providers/microsoft.powerapps/apis/shared_sharepointonline/connections/4ef7de8d4bdc40c48d41031bdc6ba8f6\"",
    "b142478a-fd3b-4ed8-8914-c9b3e1278abc": "\"/providers/Microsoft.PowerApps/apis/shared_logicflows/connections/2D90B5DFBAAA4060A3EA310AC7749413-D678C219586DEAA0\""
  },
  "LocalDatabaseReferencesAsEmpty": false,
  "LocalResourceFileNames": {
    "logo-rebeca-held": "c700763c-21cd-4f60-b0e7-a4bb41ed79a7.jpg",
    "logo-rebeca-held_1": "05d74558-9d5c-4b05-a4d6-51a83781cb94.jpg",
    "rebeca-held": "2c9df02e-5337-4466-bc91-e5db57bd80ac.jpg"
  },
  "LocalResourceRootPaths": {
    "logo-rebeca-held": "https://docserverpwaprodneu.blob.core.windows.net/c55ffe28-f07d-4508-a9ad-9323877b4958-1/resource/Assets0Images0c700763c-21cd-4f60-b0e7-a4bb41ed79a7.jpg?sv=2018-03-28&sr=b&sig=sAywMJ8rR%2Br1o5bAtImZwY8GZHQnU9dMtxXWewBpDlo%3D&spr=https&se=2023-02-28T07%3A02%3A12Z&sp=r",
    "logo-rebeca-held_1": "https://docserverpwaprodneu.blob.core.windows.net/c55ffe28-f07d-4508-a9ad-9323877b4958-1/resource/Assets0Images005d74558-9d5c-4b05-a4d6-51a83781cb94.jpg?sv=2018-03-28&sr=b&sig=fGRMi9b3Gxhpj4e7abIuuFG1yfEU7SPCi4Np1osGHZ8%3D&spr=https&se=2023-02-28T07%3A02%3A12Z&sp=r",
    "rebeca-held": "https://docserverpwaprodneu.blob.core.windows.net/c55ffe28-f07d-4508-a9ad-9323877b4958-1/resource/Assets0Images02c9df02e-5337-4466-bc91-e5db57bd80ac.jpg?sv=2018-03-28&sr=b&sig=DlFJIKdVp3e91QuKRtUsmaqthC2JdOfDG2JdQZYJpKw%3D&spr=https&se=2023-02-28T07%3A02%3A12Z&sp=r"
  },
  "OldLogoFileName": "t3bz4hsc.jpg",
  "OrderComponentMetadata": {
    "96398158e8e746fc93d8e965925c0a0b": 2,
    "b9f92939a4eb47ec81592b9123c0206a": 0,
    "f9adb5dfe499474e90614ba40a31b225": 1
  },
  "OrderComponentTemplate": {
    "96398158e8e746fc93d8e965925c0a0b": 2,
    "b9f92939a4eb47ec81592b9123c0206a": 0,
    "f9adb5dfe499474e90614ba40a31b225": 1
  },
  "OrderDataSource": {
    "_NavManu": 9,
    "00kreiranjenovoga": 0,
    "app_implatant": 6,
    "app_pacjenti": 5,
    "app_papirologija": 4,
    "app_tip_operacije": 3,
    "app_zahvat": 2,
    "ComboBoxSample": 8,
    "CustomGallerySample": 7,
    "Dokumenti": 1
  },
  "OrderGroupControls": {},
  "OrderPcfTemplate": {},
  "OrderTemplate": {},
  "OrderXMLTemplate": {
    "button": 4,
    "combobox": 9,
    "form": 7,
    "gallery": 2,
    "htmlViewer": 5,
    "icon": 6,
    "image": 0,
    "label": 1,
    "rectangle": 3,
    "text": 8
  },
  "OverridablePropertiesEntry": {
    "_broj": {},
    "_Broj_1": {},
    "_color": {},
    "_evidencija": {},
    "_footer": {},
    "_galEvidencija": {},
    "_galNaslov": {},
    "_galPodnaslov": {},
    "_galPodnaslov_1": {},
    "_galSjena": {},
    "_galSlika": {},
    "_gumb": {},
    "_headder": {},
    "_logo": {},
    "_menu": {},
    "_naslov": {},
    "_Natpis_1": {},
    "_nav": {},
    "_nav_lower": {},
    "_pacjent:_datum_rodenja_DataCard1": {},
    "_pacjent:_ime_DataCard1": {},
    "_pacjent:_prezime_DataCard1": {},
    "_pacjent_DataCard1": {},
    "_sidebar": {},
    "_sjena_1": {},
    "_text": {},
    "App": {},
    "block_1": {},
    "Button3": {},
    "DataCardKey2": {},
    "DataCardKey3": {},
    "DataCardKey4": {},
    "DataCardKey5": {},
    "DataCardKey6": {},
    "DataCardKey7": {},
    "DataCardKey8": {},
    "DataCardKey9": {},
    "DataCardValue2": {},
    "DataCardValue3": {},
    "DataCardValue4": {},
    "DataCardValue5": {},
    "DataCardValue6": {},
    "DataCardValue7": {},
    "DataCardValue8": {},
    "DataCardValue9": {},
    "ErrorMessage2": {},
    "ErrorMessage3": {},
    "ErrorMessage4": {},
    "ErrorMessage5": {},
    "ErrorMessage6": {},
    "ErrorMessage7": {},
    "ErrorMessage8": {},
    "ErrorMessage9": {},
    "Form2": {},
    "galleryTemplate1": {},
    "galleryTemplate1_1": {},
    "galleryTemplate2": {},
    "Home": {},
    "link_zahvat_DataCard1": {},
    "oper:Title_DataCard1": {},
    "oper_DataCard1": {},
    "Separator1": {},
    "sidebar_e": {},
    "sjena": {},
    "StarVisible2": {},
    "StarVisible3": {},
    "StarVisible4": {},
    "StarVisible5": {},
    "StarVisible6": {},
    "StarVisible7": {},
    "StarVisible8": {},
    "StarVisible9": {},
    "Title_DataCard1": {}
  },
  "PCFDynamicSchemaForIRRetrievalEntry": {},
  "PublishOrderIndices": {
    "_broj": 56,
    "_Broj_1": 63,
    "_color": 55,
    "_evidencija": 0,
    "_footer": 66,
    "_galEvidencija": 1,
    "_galNaslov": 4,
    "_galPodnaslov": 6,
    "_galPodnaslov_1": 7,
    "_galSjena": 5,
    "_galSlika": 3,
    "_gumb": 58,
    "_headder": 0,
    "_logo": 51,
    "_menu": 0,
    "_naslov": 52,
    "_Natpis_1": 64,
    "_nav": 53,
    "_nav_lower": 59,
    "_pacjent:_datum_rodenja_DataCard1": 30,
    "_pacjent:_ime_DataCard1": 20,
    "_pacjent:_prezime_DataCard1": 25,
    "_pacjent_DataCard1": 15,
    "_sidebar": 0,
    "_sjena_1": 61,
    "_text": 57,
    "App": 0,
    "block_1": 62,
    "Button3": 65,
    "DataCardKey2": 12,
    "DataCardKey3": 17,
    "DataCardKey4": 22,
    "DataCardKey5": 27,
    "DataCardKey6": 32,
    "DataCardKey7": 37,
    "DataCardKey8": 42,
    "DataCardKey9": 47,
    "DataCardValue2": 13,
    "DataCardValue3": 18,
    "DataCardValue4": 23,
    "DataCardValue5": 28,
    "DataCardValue6": 33,
    "DataCardValue7": 38,
    "DataCardValue8": 43,
    "DataCardValue9": 48,
    "ErrorMessage2": 14,
    "ErrorMessage3": 19,
    "ErrorMessage4": 24,
    "ErrorMessage5": 29,
    "ErrorMessage6": 34,
    "ErrorMessage7": 39,
    "ErrorMessage8": 44,
    "ErrorMessage9": 49,
    "Form2": 9,
    "galleryTemplate1": 54,
    "galleryTemplate1_1": 60,
    "galleryTemplate2": 2,
    "Home": 0,
    "link_zahvat_DataCard1": 45,
    "oper:Title_DataCard1": 40,
    "oper_DataCard1": 35,
    "Separator1": 8,
    "sidebar_e": 0,
    "sjena": 50,
    "StarVisible2": 11,
    "StarVisible3": 16,
    "StarVisible4": 21,
    "StarVisible5": 26,
    "StarVisible6": 31,
    "StarVisible7": 36,
    "StarVisible8": 41,
    "StarVisible9": 46,
    "Title_DataCard1": 10
  },
  "ResourcesJsonIndices": {
    "Image-logo-rebeca-held": 1,
    "Image-logo-rebeca-held_1": 2,
    "Image-rebeca-held": 3,
    "Image-SampleImage": 0
  },
  "RuleScreenIdWithoutScreen": {},
  "TemplateVersions": {},
  "VolatileProperties": {
    "AnalysisLoadTime": 0.2040983,
    "ControlCount": {
      "96398158e8e746fc93d8e965925c0a0b": 2,
      "b9f92939a4eb47ec81592b9123c0206a": 1,
      "button": 2,
      "f9adb5dfe499474e90614ba40a31b225": 1,
      "gallery": 3,
      "galleryTemplate": 3,
      "htmlViewer": 1,
      "icon": 1,
      "image": 2,
      "label": 9,
      "rectangle": 4,
      "screen": 2
    },
    "DeserializationLoadTime": 0.9887593,
    "ErrorCount": 1
  },
  "WasLocalDatabaseReferencesEmpty": true
}